TypeSaveArgParse/__init__.py
TypeSaveArgParse/autoargs.py
TypeSaveArgParse/utils.py
typesaveargparse-1.0.3.dist-info/LICENSE
typesaveargparse-1.0.3.dist-info/METADATA
typesaveargparse-1.0.3.dist-info/WHEEL
typesaveargparse-1.0.3.dist-info/RECORD
