Metadata-Version: 2.3
Name: TypeSaveArgParse
Version: 1.0.3
Summary: A tool to get programm arguments by defining dataclasses with type save annotation.
License: MIT
Author: Robert Graf
Author-email: robert.graf@tum.de
Requires-Python: >=3.9,<4.0
Classifier: License :: OSI Approved :: MIT License
Classifier: Programming Language :: Python :: 3
Classifier: Programming Language :: Python :: 3.9
Classifier: Programming Language :: Python :: 3.10
Classifier: Programming Language :: Python :: 3.11
Classifier: Programming Language :: Python :: 3.12
Classifier: Programming Language :: Python :: 3.13
Requires-Dist: ConfigArgParse
Requires-Dist: PyYAML
Requires-Dist: docstring_parser
Requires-Dist: pathlib
Requires-Dist: ruamel.yaml
Project-URL: Repository, https://github.com/robert-graf/TypeSaveArgParse
